.gitignore
.gitlab-ci.yml
LICENSE.rst
MANIFEST.in
README.rst
README_WINDOWS.txt
benchmark.py
setup.cfg
setup.py
test_tinyarray.py
version
src/arithmetic.cc
src/arithmetic.hh
src/array.cc
src/array.hh
src/conversion.hh
src/functions.cc
src/functions.hh
tinyarray.egg-info/PKG-INFO
tinyarray.egg-info/SOURCES.txt
tinyarray.egg-info/dependency_links.txt
tinyarray.egg-info/top_level.txt