Metadata-Version: 2.1
Name: tinyarray
Version: 1.2.5
Summary: Arrays of numbers for Python, optimized for small sizes
Home-page: https://gitlab.kwant-project.org/kwant/tinyarray
Download-URL: http://downloads.kwant-project.org/tinyarray/
Author: Christoph Groth (CEA) and others
Author-email: christoph.groth@cea.fr
License: Simplified BSD license
Platform: Unix
Platform: Linux
Platform: Mac OS-X
Platform: Windows
Classifier:     Development Status :: 5 - Production/Stable
Classifier:     Intended Audience :: Science/Research
Classifier:     Intended Audience :: Developers
Classifier:     License :: OSI Approved :: BSD License
Classifier:     Programming Language :: Python :: 2
Classifier:     Programming Language :: Python :: 3
Classifier:     Programming Language :: C++
Classifier:     Topic :: Software Development
Classifier:     Topic :: Scientific/Engineering
Classifier:     Operating System :: POSIX
Classifier:     Operating System :: Unix
Classifier:     Operating System :: MacOS
Classifier:     Operating System :: Microsoft :: Windows
License-File: LICENSE.rst
